lexicons_builder/__init__.py
lexicons_builder/__main__.py
lexicons_builder/graphs/__init__.py
lexicons_builder/graphs/graphs.py
lexicons_builder/nlp_model_explorer/__init__.py
lexicons_builder/nlp_model_explorer/explorer.py
lexicons_builder/scrappers/__init__.py
lexicons_builder/scrappers/scrappers.py
lexicons_builder/touch_file/__init__.py
lexicons_builder/touch_file/touch_file.py
lexicons_builder/wordnet_explorer/__init__.py
lexicons_builder/wordnet_explorer/_frenetic.py
lexicons_builder/wordnet_explorer/explorer.py
lexicons_builder-0.3.2.dist-info/AUTHORS.rst
lexicons_builder-0.3.2.dist-info/LICENSE.txt
lexicons_builder-0.3.2.dist-info/METADATA
lexicons_builder-0.3.2.dist-info/WHEEL
lexicons_builder-0.3.2.dist-info/top_level.txt
lexicons_builder-0.3.2.dist-info/RECORD
