Metadata-Version: 2.1
Name: lexicons-builder
Version: 0.3.2
Summary: lexicons_builder, a tool to create lexicons
Home-page: https://lexicons-builder.readthedocs.io
Author: GLNB
Author-email: glnb.dev@gmail.com
License: MIT
Project-URL: Documentation, https://lexicons-builder.readthedocs.io
Project-URL: Source, https://github.com/GuillaumeLNB/lexicons_builder
Platform: UNKNOWN
Requires-Dist: gensim
Requires-Dist: languagecodes
Requires-Dist: touch
Requires-Dist: unidecode
Requires-Dist: sphinx-rtd-theme
Requires-Dist: parameterized
Requires-Dist: nltk
Requires-Dist: rdflib
Requires-Dist: requests
Requires-Dist: beautifulsoup4
Requires-Dist: banal
Requires-Dist: xlsxwriter
Requires-Dist: bs4
